README.md
aio_meilisearch/__init__.py
aio_meilisearch/common.py
aio_meilisearch/exceptions.py
aio_meilisearch/models.py
aio_meilisearch/settings.py
aio_meilisearch/types.py
aio_meilisearch-0.1.1.dist-info/WHEEL
aio_meilisearch-0.1.1.dist-info/METADATA
aio_meilisearch-0.1.1.dist-info/RECORD
