Metadata-Version: 2.1
Name: aio-meilisearch
Version: 0.1.1
Summary: Async library for MeiliSearch
Home-page: https://github.com/devtud/aio_meilisearch
License: MIT
Keywords: asyncio,meilisearch
Author: devtud
Author-email: devtud@gmail.com
Requires-Python: >=3.8,<4.0
Classifier: Development Status :: 3 - Alpha
Classifier: Framework :: AsyncIO
Classifier: Intended Audience :: Developers
Classifier: License :: OSI Approved :: MIT License
Classifier: Programming Language :: Python :: 3
Classifier: Programming Language :: Python :: 3 :: Only
Classifier: Programming Language :: Python :: 3.8
Classifier: Programming Language :: Python :: 3.9
Classifier: Topic :: Software Development :: Libraries :: Application Frameworks
Requires-Dist: httpx
Project-URL: Repository, https://github.com/devtud/aio_meilisearch
